SdnWangluoZhinan/README.md
SdnWangluoZhinan/__init__.py
SdnWangluoZhinan/__main__.py
SdnWangluoZhinan/file.epub
SdnWangluoZhinan/index.html
SdnWangluoZhinan/css/__init__.py
SdnWangluoZhinan/css/annotations.css
SdnWangluoZhinan/css/main.css
SdnWangluoZhinan/css/normalize.css
SdnWangluoZhinan/css/popup.css
SdnWangluoZhinan/font/__init__.py
SdnWangluoZhinan/font/fontello.eot
SdnWangluoZhinan/font/fontello.svg
SdnWangluoZhinan/font/fontello.ttf
SdnWangluoZhinan/font/fontello.woff
SdnWangluoZhinan/img/__init__.py
SdnWangluoZhinan/img/annotator-glyph-sprite.png
SdnWangluoZhinan/img/annotator-icon-sprite.png
SdnWangluoZhinan/img/apple-touch-icon.png
SdnWangluoZhinan/img/cancelfullscreen.png
SdnWangluoZhinan/img/close.png
SdnWangluoZhinan/img/fullscreen.png
SdnWangluoZhinan/img/loader.gif
SdnWangluoZhinan/img/menu-icon.png
SdnWangluoZhinan/img/save.png
SdnWangluoZhinan/img/saved.png
SdnWangluoZhinan/img/settings-s.png
SdnWangluoZhinan/img/settings.png
SdnWangluoZhinan/img/star.png
SdnWangluoZhinan/js/__init__.py
SdnWangluoZhinan/js/epub.js
SdnWangluoZhinan/js/epub.min.js
SdnWangluoZhinan/js/epub.min.map
SdnWangluoZhinan/js/hooks.min.js
SdnWangluoZhinan/js/hooks.min.map
SdnWangluoZhinan/js/reader.js
SdnWangluoZhinan/js/reader.js.map
SdnWangluoZhinan/js/reader.min.js
SdnWangluoZhinan/js/reader.min.map
SdnWangluoZhinan/js/hooks/__init__.py
SdnWangluoZhinan/js/hooks/extensions/__init__.py
SdnWangluoZhinan/js/hooks/extensions/highlight.js
SdnWangluoZhinan/js/libs/__init__.py
SdnWangluoZhinan/js/libs/jquery.min.js
SdnWangluoZhinan/js/libs/localforage.min.js
SdnWangluoZhinan/js/libs/screenfull.js
SdnWangluoZhinan/js/libs/screenfull.min.js
SdnWangluoZhinan/js/libs/zip.min.js
SdnWangluoZhinan/js/plugins/__init__.py
SdnWangluoZhinan/js/plugins/hypothesis.js
SdnWangluoZhinan/js/plugins/search.js
sdn_wangluo_zhinan-2024.3.3.0.dist-info/METADATA
sdn_wangluo_zhinan-2024.3.3.0.dist-info/WHEEL
sdn_wangluo_zhinan-2024.3.3.0.dist-info/entry_points.txt
sdn_wangluo_zhinan-2024.3.3.0.dist-info/top_level.txt
sdn_wangluo_zhinan-2024.3.3.0.dist-info/RECORD
